LICENSE
README.md
requirements.txt
setup.py
fve_layer/__init__.py
fve_layer.egg-info/PKG-INFO
fve_layer.egg-info/SOURCES.txt
fve_layer.egg-info/dependency_links.txt
fve_layer.egg-info/not-zip-safe
fve_layer.egg-info/requires.txt
fve_layer.egg-info/top_level.txt
fve_layer/backends/__init__.py
fve_layer/backends/chainer/__init__.py
fve_layer/backends/chainer/functions/__init__.py
fve_layer/backends/chainer/links/__init__.py
fve_layer/backends/chainer/links/base.py
fve_layer/backends/chainer/links/fve.py
fve_layer/backends/chainer/links/gmm.py
fve_layer/common/__init__.py
fve_layer/common/visualization.py
fve_layer/common/mixtures/__init__.py
fve_layer/common/mixtures/base.py
fve_layer/common/mixtures/bayesian.py
fve_layer/common/mixtures/gaussian.py
tests/__init__.py
tests/base.py
tests/fve_tests.py
tests/gmm_tests.py